philiarabbit/base.py
philiarabbit/connection_pool.py
philiarabbit/consumer.py
philiarabbit/producer.py
philiarabbit-0.2.2.dist-info/METADATA
philiarabbit-0.2.2.dist-info/WHEEL
philiarabbit-0.2.2.dist-info/RECORD
