Metadata-Version: 2.1
Name: philiarabbit
Version: 0.2.2
Summary: 
Author: Amir RedHat
Author-email: amir.ch.charehei1382@gmail.com
Requires-Python: >=3.13,<4.0
Classifier: Programming Language :: Python :: 3
Requires-Dist: aio-pika (>=9.5.7,<10.0.0)
Requires-Dist: flask[async] (>=3.1.2,<4.0.0)
Requires-Dist: pika (>=1.3.2,<2.0.0)
